pycounts_chen_test/__init__.py
pycounts_chen_test/plotting.py
pycounts_chen_test/pycounts_chen_test.py
pycounts_chen_test-0.1.0.dist-info/LICENSE
pycounts_chen_test-0.1.0.dist-info/METADATA
pycounts_chen_test-0.1.0.dist-info/WHEEL
pycounts_chen_test-0.1.0.dist-info/RECORD
